hamster_lib/__init__.py
hamster_lib/lib.py
hamster_lib/objects.py
hamster_lib/reports.py
hamster_lib/storage.py
hamster_lib/backends/__init__.py
hamster_lib/backends/sqlalchemy/__init__.py
hamster_lib/backends/sqlalchemy/objects.py
hamster_lib/backends/sqlalchemy/storage.py
hamster_lib/helpers/__init__.py
hamster_lib/helpers/config_helpers.py
hamster_lib/helpers/helpers.py
hamster_lib/helpers/time.py
hamster_lib-0.13.2.dist-info/DESCRIPTION.rst
hamster_lib-0.13.2.dist-info/METADATA
hamster_lib-0.13.2.dist-info/RECORD
hamster_lib-0.13.2.dist-info/WHEEL
hamster_lib-0.13.2.dist-info/metadata.json
hamster_lib-0.13.2.dist-info/top_level.txt
tests/__init__.py
tests/conftest.py
tests/backends/__init__.py
tests/backends/sqlalchemy/__init__.py
tests/backends/sqlalchemy/common.py
tests/backends/sqlalchemy/conftest.py
tests/backends/sqlalchemy/factories.py
tests/backends/sqlalchemy/test_objects.py
tests/backends/sqlalchemy/test_storage.py
tests/hamster_lib/__init__.py
tests/hamster_lib/conftest.py
tests/hamster_lib/factories.py
tests/hamster_lib/test_lib.py
tests/hamster_lib/test_objects.py
tests/hamster_lib/test_reports.py
tests/hamster_lib/test_storage.py
tests/helpers/__init__.py
tests/helpers/conftest.py
tests/helpers/test_config_helpers.py
tests/helpers/test_helpers.py
tests/helpers/test_time.py
