Metadata-Version: 2.0
Name: hamster-lib
Version: 0.13.2
Summary: A library for common timetracking functionality.
Home-page: https://github.com/projecthamster/hamster-lib
Author: Eric Goller
Author-email: eric.goller@ninjaduck.solutions
License: GPL3
Keywords: hamster-lib
Platform: UNKNOWN
Classifier: Development Status :: 2 - Pre-Alpha
Classifier: Intended Audience :: Developers
Classifier: License :: OSI Approved :: GNU General Public License v3 (GPLv3)
Classifier: Natural Language :: English
Classifier: Programming Language :: Python :: 2
Classifier: Programming Language :: Python :: 2.7
Classifier: Programming Language :: Python :: 3
Classifier: Programming Language :: Python :: 3.4
Requires-Dist: appdirs
Requires-Dist: configparser (>=3.5.0b2)
Requires-Dist: future
Requires-Dist: icalendar
Requires-Dist: six
Requires-Dist: sqlalchemy
